ichs/ICHS.py
ichs/__init__.py
ichs-1.7.1.dist-info/LICENCE
ichs-1.7.1.dist-info/METADATA
ichs-1.7.1.dist-info/WHEEL
ichs-1.7.1.dist-info/top_level.txt
ichs-1.7.1.dist-info/RECORD
