Metadata-Version: 2.1
Name: ichs
Version: 1.7.1
Summary: A Python module Based on Ilford County High School
Home-page: https://github.com/Custom/ichs
Author: Diwan Mohamed Faheer
Author-email: diwanmohamedfaheer@gmail.com
License: UNKNOWN
Platform: UNKNOWN
Classifier: Programming Language :: Python :: 3
Classifier: License :: OSI Approved :: MIT License
Classifier: Operating System :: OS Independent
Requires-Python: >=3.6
